{
  "timestamp": "2026-03-07T06:34:53.525272",
  "business_profile": {
    "services": [
      "Fractional CMO",
      "AI Agent Building",
      "Marketing Automation",
      "Growth Strategy"
    ],
    "target_clients": "Startups, Series A/B companies",
    "current_channels": {
      "lead_generation": [
        "Reddit",
        "Upwork (pending)",
        "X/Twitter (pending)"
      ],
      "communication": [
        "Email",
        "Telegram",
        "Webchat"
      ],
      "automation": [
        "OpenClaw",
        "Gmail API",
        "SQLite database"
      ]
    }
  },
  "operational_analysis": {
    "strengths": [
      "Automated lead discovery (CRO skill)",
      "Multi-channel communication setup",
      "Security monitoring (CSO)",
      "API cost tracking",
      "Documented processes (SKILL.md files)"
    ],
    "gaps": [
      "No formal pricing structure documented",
      "No client onboarding process defined",
      "No retention/upsell system",
      "Revenue tracking manual/informal",
      "No productized service packages"
    ]
  },
  "immediate_opportunities": [
    {
      "opportunity": "AI Treasurer Service",
      "inspiration": "From Mike Russell video",
      "description": "Monthly oversight of client AI spend and agent performance",
      "price_point": "$1,500-3,000/month",
      "effort": "Medium",
      "impact": "High"
    },
    {
      "opportunity": "AI Team Design Package",
      "description": "2-week engagement to architect 3-agent system for client",
      "price_point": "$5,000-8,000 one-time",
      "effort": "Medium",
      "impact": "High"
    },
    {
      "opportunity": "Client Community",
      "description": "Paid community for current/past clients ($99/month)",
      "price_point": "$99/month per member",
      "effort": "Low",
      "impact": "Medium"
    },
    {
      "opportunity": "Content from Client Work",
      "description": "Document experiments as case studies (with permission)",
      "price_point": "Free marketing",
      "effort": "Low",
      "impact": "Medium"
    }
  ],
  "pricing_recommendations": {
    "current_state": "Unclear / project-based",
    "recommended_structure": {
      "tier_1_discovery": "$2,500-5,000 (2-4 week audit/strategy)",
      "tier_2_implementation": "$5,000-15,000 (AI agent build)",
      "tier_3_ongoing": "$3,000-8,000/month (fractional CMO retainer)",
      "tier_4_premium": "$10,000+/month (AI ecosystem oversight)"
    }
  },
  "next_steps": [
    "Document current pricing and packages",
    "Create AI Treasurer service offering",
    "Design client onboarding checklist",
    "Set up revenue tracking spreadsheet",
    "Draft LinkedIn case study from first client"
  ]
}